{"nodes": [{"id": "home_zerg_stm32cubeide_workspace_1_15_1_zagotovka_m_core_src_freertos_c", "label": "freertos.c", "file_type": "code", "source_file": "Core/Src/freertos.c", "source_location": "L1"}, {"id": "src_freertos_sof_putchar", "label": "sof_putchar()", "file_type": "code", "source_file": "Core/Src/freertos.c", "source_location": "L63"}, {"id": "src_freertos_sof_puts", "label": "sof_puts()", "file_type": "code", "source_file": "Core/Src/freertos.c", "source_location": "L71"}, {"id": "src_freertos_vapplicationstackoverflowhook", "label": "vApplicationStackOverflowHook()", "file_type": "code", "source_file": "Core/Src/freertos.c", "source_location": "L78"}, {"id": "taskhandle_t", "label": "TaskHandle_t", "file_type": "code", "source_file": "Core/Src/freertos.c", "source_location": "L78"}], "edges": [{"source": "home_zerg_stm32cubeide_workspace_1_15_1_zagotovka_m_core_src_freertos_c", "target": "freertos", "relation": "imports", "context": "import", "confidence": "EXTRACTED", "source_file": "Core/Src/freertos.c", "source_location": "L21", "weight": 1.0}, {"source": "home_zerg_stm32cubeide_workspace_1_15_1_zagotovka_m_core_src_freertos_c", "target": "task", "relation": "imports", "context": "import", "confidence": "EXTRACTED", "source_file": "Core/Src/freertos.c", "source_location": "L22", "weight": 1.0}, {"source": "home_zerg_stm32cubeide_workspace_1_15_1_zagotovka_m_core_src_freertos_c", "target": "main", "relation": "imports", "context": "import", "confidence": "EXTRACTED", "source_file": "Core/Src/freertos.c", "source_location": "L23", "weight": 1.0}, {"source": "home_zerg_stm32cubeide_workspace_1_15_1_zagotovka_m_core_src_freertos_c", "target": "src_freertos_sof_putchar", "relation": "contains", "confidence": "EXTRACTED", "source_file": "Core/Src/freertos.c", "source_location": "L63", "weight": 1.0}, {"source": "home_zerg_stm32cubeide_workspace_1_15_1_zagotovka_m_core_src_freertos_c", "target": "src_freertos_sof_puts", "relation": "contains", "confidence": "EXTRACTED", "source_file": "Core/Src/freertos.c", "source_location": "L71", "weight": 1.0}, {"source": "home_zerg_stm32cubeide_workspace_1_15_1_zagotovka_m_core_src_freertos_c", "target": "src_freertos_vapplicationstackoverflowhook", "relation": "contains", "confidence": "EXTRACTED", "source_file": "Core/Src/freertos.c", "source_location": "L78", "weight": 1.0}, {"source": "src_freertos_vapplicationstackoverflowhook", "target": "taskhandle_t", "relation": "references", "confidence": "EXTRACTED", "source_file": "Core/Src/freertos.c", "source_location": "L78", "weight": 1.0, "context": "parameter_type"}, {"source": "src_freertos_sof_puts", "target": "src_freertos_sof_putchar", "relation": "calls", "context": "call", "confidence": "EXTRACTED", "source_file": "Core/Src/freertos.c", "source_location": "L73", "weight": 1.0}, {"source": "src_freertos_vapplicationstackoverflowhook", "target": "src_freertos_sof_puts", "relation": "calls", "context": "call", "confidence": "EXTRACTED", "source_file": "Core/Src/freertos.c", "source_location": "L81", "weight": 1.0}, {"source": "src_freertos_vapplicationstackoverflowhook", "target": "src_freertos_sof_putchar", "relation": "calls", "context": "call", "confidence": "EXTRACTED", "source_file": "Core/Src/freertos.c", "source_location": "L94", "weight": 1.0}], "raw_calls": [{"caller_nid": "src_freertos_vapplicationstackoverflowhook", "callee": "__disable_irq", "is_member_call": false, "source_file": "/home/zerg/STM32CubeIDE/workspace_1.15.1/Zagotovka_M/Core/Src/freertos.c", "source_location": "L106"}, {"caller_nid": "src_freertos_vapplicationstackoverflowhook", "callee": "HAL_GPIO_TogglePin", "is_member_call": false, "source_file": "/home/zerg/STM32CubeIDE/workspace_1.15.1/Zagotovka_M/Core/Src/freertos.c", "source_location": "L109"}, {"caller_nid": "src_freertos_vapplicationstackoverflowhook", "callee": "HAL_GPIO_TogglePin", "is_member_call": false, "source_file": "/home/zerg/STM32CubeIDE/workspace_1.15.1/Zagotovka_M/Core/Src/freertos.c", "source_location": "L110"}, {"caller_nid": "src_freertos_vapplicationstackoverflowhook", "callee": "HAL_GPIO_TogglePin", "is_member_call": false, "source_file": "/home/zerg/STM32CubeIDE/workspace_1.15.1/Zagotovka_M/Core/Src/freertos.c", "source_location": "L112"}, {"caller_nid": "src_freertos_vapplicationstackoverflowhook", "callee": "HAL_GPIO_TogglePin", "is_member_call": false, "source_file": "/home/zerg/STM32CubeIDE/workspace_1.15.1/Zagotovka_M/Core/Src/freertos.c", "source_location": "L113"}]}